Verilog/Subtractor/Half Subtractor/half_subtractor.v
module half_subtractor(
    input i0, i1,
    output d, bout);

    assign d = i0 ^ i1;
    assign bout = ~i0 & i1;
endmodule

Verilog/Subtractor/Full Subtractor/full_subtractor.v
`include "Subtractor/Half Subtractor/half_subtractor.v"

module full_subtractor(
    input i0, i1, bin,
    output d, bout);

    wire d1, b1, b2;
    half_subtractor hs0(i0, i1, d1, b1);
    half_subtractor hs1(d1, bin, d, b2);

    or o(bout, b1, b2);

endmodule

Verilog/Subtractor/Full Subtractor/full_subtractor_tb.v
`include "Subtractor/Full Subtractor/full_subtractor.v"

module full_subtractor_tb;
    reg i0, i1, bin;
    wire d, bout;

    full_subtractor fs(i0, i1, bin, d, bout);

    initial begin
        $dumpfile("full_subtractor_tb.vcd");
        $dumpvars(0, full_subtractor_tb);

        i0 = 0; i1 = 0; bin = 0;
        #1

        i0 = 0; i1 = 0; bin = 1;
        #1

        i0 = 0; i1 = 1; bin = 0;
        #1

        i0 = 1; i1 = 0; bin = 0;
        #1

        i0 = 0; i1 = 1; bin = 1;
        #1

        i0 = 1; i1 = 0; bin = 1;
        #1

        i0 = 1; i1 = 1; bin = 0;
        #1

        i0 = 1; i1 = 1; bin = 1;
    end

endmodule

Verilog/Subtractor/Full Subtractor/full_subtractor_tb.vcd
$date
	Thu Jan 05 16:09:20 2023
$end
$version
	Icarus Verilog
$end
$timescale
	1s
$end
$scope module full_subtractor_tb $end
$var wire 1 ! d $end
$var wire 1 " bout $end
$var reg 1 # bin $end
$var reg 1 $ i0 $end
$var reg 1 % i1 $end
$scope module fs $end
$var wire 1 # bin $end
$var wire 1 " bout $end
$var wire 1 $ i0 $end
$var wire 1 % i1 $end
$var wire 1 & d1 $end
$var wire 1 ! d $end
$var wire 1 ' b2 $end
$var wire 1 ( b1 $end
$scope module hs0 $end
$var wire 1 ( bout $end
$var wire 1 & d $end
$var wire 1 $ i0 $end
$var wire 1 % i1 $end
$upscope $end
$scope module hs1 $end
$var wire 1 ' bout $end
$var wire 1 ! d $end
$var wire 1 & i0 $end
$var wire 1 # i1 $end
$upscope $end
$upscope $end
$upscope $end
$enddefinitions $end
$comment Show the parameter values. $end
$dumpall
$end
#0
$dumpvars
0(
0'
0&
0%
0$
0#
0"
0!
$end
#1
1"
1!
1'
1#
#2
0'
1&
1(
0#
1%
#3
0"
0(
0%
1$
#4
1"
0!
1(
1#
1%
0$
#5
0"
0(
0%
1$
#6
0&
0#
1%
#7
1"
1!
1'
1#
