Verilog/Subtractor/Half Subtractor/half_subtractor.v
module half_subtractor(
    input i0, i1,
    output d, bout
);

    assign d = i0 ^ i1;
    assign bout = ~i0 & i1;
endmodule

Verilog/Subtractor/Decrementer/ten_bit_decrementer.v
`include "Subtractor/Half Subtractor/half_subtractor.v"

module ten_bit_decrementer(
    input [9:0] a,
    output [9:0] s,
    output o);

    wire [9:0] b;

    half_subtractor hs0(a[0], 1'b1, s[0],b[0]);

    genvar i;

    generate
        for(i = 1; i < 10; i = i + 1) begin
            half_subtractor hsi(a[i], b[i - 1], s[i], b[i]);
        end
    endgenerate

    assign o = b[9];
endmodule

Verilog/Adder/Half Adder/half_adder.v
module half_adder(i0, i1, s, cout);
    input i0, i1;
    output s, cout;

    xor x(s, i0, i1);
    and a(cout, i0, i1);
endmodule

Verilog/Adder/Incrementer/ten_bit_incrementer.v
`include "../Half Adder/half_adder.v"

module ten_bit_incrementer(
    input [9:0] a,
    output [9:0] s,
    output o
);

    wire [9:0] c;

    half_adder ha0(1'b1, a[0], s[0], c[0]);

    genvar i;

    generate
        for(i = 1; i < 10; i = i + 1) begin
            half_adder hai(c[i - 1], a[i], s[i], c[i]);
        end
    endgenerate

    assign o = c[9];

endmodule

Verilog/Latches/Rising Edge Triggered D Flip-Flop/rising_edge_triggered_d_flipflop.v
module rising_edge_triggered_d_flipflop(
    input d, w, clk,
    output reg q);

    initial begin
        q = 0;
    end

    always @(posedge clk) begin
        if(w)
            q <= d;
    end
endmodule

Verilog/Registers/10 Bit Register/ten_bit_register.v
`include "Latches/Rising Edge Triggered D Flip-Flop/rising_edge_triggered_d_flipflop.v"

module ten_bit_register#(
    parameter [9:0] INIT = 10'd0
)(
    input [9:0] d,
    input clk, w,
    output reg [9:0] q);

    initial begin
        q = INIT;
    end

    always @(posedge clk) begin
        if(w)
            q <= d;
    end
endmodule

Verilog/Control Unit/Stack Pointer/stack_pointer.v
`include "Adder/Incrementer/ten_bit_incrementer.v"
`include "Subtractor/Decrementer/ten_bit_decrementer.v"
`include "Registers/10 Bit Register/ten_bit_register.v"

module stack_pointer(
    input push, pop, clk,
    output [9:0] SP,
    output stack_overflow);

    wire w_enabled, incr_overflow, decr_overflow, push_overflow, pop_overflow;
    wire [9:0] incr_q, decr_q;

    or(w_enabled, push, pop);

    ten_bit_register #(.INIT(10'd1023)) sp(.d(push ? decr_q : incr_q), .clk(clk), .w(w_enabled), .q(SP));

    ten_bit_incrementer incr(SP, incr_q, incr_overflow);
    ten_bit_decrementer decr(SP, decr_q, decr_overflow);

    and(push_overflow, decr_overflow, push);
    and(pop_overflow, incr_overflow, pop);
    or(stack_overflow, push_overflow, pop_overflow);
endmodule

Verilog/Control Unit/Stack Pointer/stack_pointer_tb.v
`timescale 1ns/1ns
`include "Control Unit/Stack Pointer/stack_pointer.v"

module stack_pointer_tb;
    reg push, pop, clk;
    wire [9:0] SP;
    wire stack_overflow;

    stack_pointer sp(push, pop, clk, SP, stack_overflow);

    initial begin
        clk = 0;
        forever #1 clk = ~clk;
    end

    initial begin
        $dumpfile("stack_pointer_tb.vcd");
        $dumpvars(0, stack_pointer_tb);

        push = 1; pop = 0;
        #15

        pop = 1; push = 0;
        #10

        push = 1; pop = 0;
        #25

        push = 0; pop = 1;
        #40

        $finish;
    end

endmodule

Verilog/Control Unit/Stack Pointer/stack_pointer_tb.vcd
$date
	Sat Jan 07 08:52:18 2023
$end
$version
	Icarus Verilog
$end
$timescale
	1ns
$end
$scope module stack_pointer_tb $end
$var wire 1 ! stack_overflow $end
$var wire 10 " SP [9:0] $end
$var reg 1 # clk $end
$var reg 1 $ pop $end
$var reg 1 % push $end
$scope module sp $end
$var wire 1 # clk $end
$var wire 1 $ pop $end
$var wire 1 & pop_overflow $end
$var wire 1 % push $end
$var wire 1 ' push_overflow $end
$var wire 1 ! stack_overflow $end
$var wire 1 ( w_enabled $end
$var wire 10 ) incr_q [9:0] $end
$var wire 1 * incr_overflow $end
$var wire 10 + decr_q [9:0] $end
$var wire 1 , decr_overflow $end
$var wire 10 - SP [9:0] $end
$scope module decr $end
$var wire 10 . s [9:0] $end
$var wire 1 , o $end
$var wire 10 / b [9:0] $end
$var wire 10 0 a [9:0] $end
$scope begin genblk1[1] $end
$var parameter 2 1 i $end
$scope module hsi $end
$var wire 1 2 bout $end
$var wire 1 3 d $end
$var wire 1 4 i0 $end
$var wire 1 5 i1 $end
$upscope $end
$upscope $end
$scope begin genblk1[2] $end
$var parameter 3 6 i $end
$scope module hsi $end
$var wire 1 7 bout $end
$var wire 1 8 d $end
$var wire 1 9 i0 $end
$var wire 1 : i1 $end
$upscope $end
$upscope $end
$scope begin genblk1[3] $end
$var parameter 3 ; i $end
$scope module hsi $end
$var wire 1 < bout $end
$var wire 1 = d $end
$var wire 1 > i0 $end
$var wire 1 ? i1 $end
$upscope $end
$upscope $end
$scope begin genblk1[4] $end
$var parameter 4 @ i $end
$scope module hsi $end
$var wire 1 A bout $end
$var wire 1 B d $end
$var wire 1 C i0 $end
$var wire 1 D i1 $end
$upscope $end
$upscope $end
$scope begin genblk1[5] $end
$var parameter 4 E i $end
$scope module hsi $end
$var wire 1 F bout $end
$var wire 1 G d $end
$var wire 1 H i0 $end
$var wire 1 I i1 $end
$upscope $end
$upscope $end
$scope begin genblk1[6] $end
$var parameter 4 J i $end
$scope module hsi $end
$var wire 1 K bout $end
$var wire 1 L d $end
$var wire 1 M i0 $end
$var wire 1 N i1 $end
$upscope $end
$upscope $end
$scope begin genblk1[7] $end
$var parameter 4 O i $end
$scope module hsi $end
$var wire 1 P bout $end
$var wire 1 Q d $end
$var wire 1 R i0 $end
$var wire 1 S i1 $end
$upscope $end
$upscope $end
$scope begin genblk1[8] $end
$var parameter 5 T i $end
$scope module hsi $end
$var wire 1 U bout $end
$var wire 1 V d $end
$var wire 1 W i0 $end
$var wire 1 X i1 $end
$upscope $end
$upscope $end
$scope begin genblk1[9] $end
$var parameter 5 Y i $end
$scope module hsi $end
$var wire 1 Z bout $end
$var wire 1 [ d $end
$var wire 1 \ i0 $end
$var wire 1 ] i1 $end
$upscope $end
$upscope $end
$scope module hs0 $end
$var wire 1 ^ bout $end
$var wire 1 _ d $end
$var wire 1 ` i0 $end
$var wire 1 a i1 $end
$upscope $end
$upscope $end
$scope module incr $end
$var wire 10 b s [9:0] $end
$var wire 1 * o $end
$var wire 10 c c [9:0] $end
$var wire 10 d a [9:0] $end
$scope begin genblk1[1] $end
$var parameter 2 e i $end
$scope module hai $end
$var wire 1 f cout $end
$var wire 1 g i0 $end
$var wire 1 h i1 $end
$var wire 1 i s $end
$upscope $end
$upscope $end
$scope begin genblk1[2] $end
$var parameter 3 j i $end
$scope module hai $end
$var wire 1 k cout $end
$var wire 1 l i0 $end
$var wire 1 m i1 $end
$var wire 1 n s $end
$upscope $end
$upscope $end
$scope begin genblk1[3] $end
$var parameter 3 o i $end
$scope module hai $end
$var wire 1 p cout $end
$var wire 1 q i0 $end
$var wire 1 r i1 $end
$var wire 1 s s $end
$upscope $end
$upscope $end
$scope begin genblk1[4] $end
$var parameter 4 t i $end
$scope module hai $end
$var wire 1 u cout $end
$var wire 1 v i0 $end
$var wire 1 w i1 $end
$var wire 1 x s $end
$upscope $end
$upscope $end
$scope begin genblk1[5] $end
$var parameter 4 y i $end
$scope module hai $end
$var wire 1 z cout $end
$var wire 1 { i0 $end
$var wire 1 | i1 $end
$var wire 1 } s $end
$upscope $end
$upscope $end
$scope begin genblk1[6] $end
$var parameter 4 ~ i $end
$scope module hai $end
$var wire 1 !" cout $end
$var wire 1 "" i0 $end
$var wire 1 #" i1 $end
$var wire 1 $" s $end
$upscope $end
$upscope $end
$scope begin genblk1[7] $end
$var parameter 4 %" i $end
$scope module hai $end
$var wire 1 &" cout $end
$var wire 1 '" i0 $end
$var wire 1 (" i1 $end
$var wire 1 )" s $end
$upscope $end
$upscope $end
$scope begin genblk1[8] $end
$var parameter 5 *" i $end
$scope module hai $end
$var wire 1 +" cout $end
$var wire 1 ," i0 $end
$var wire 1 -" i1 $end
$var wire 1 ." s $end
$upscope $end
$upscope $end
$scope begin genblk1[9] $end
$var parameter 5 /" i $end
$scope module hai $end
$var wire 1 0" cout $end
$var wire 1 1" i0 $end
$var wire 1 2" i1 $end
$var wire 1 3" s $end
$upscope $end
$upscope $end
$scope module ha0 $end
$var wire 1 4" cout $end
$var wire 1 5" i0 $end
$var wire 1 6" i1 $end
$var wire 1 7" s $end
$upscope $end
$upscope $end
$scope module sp $end
$var wire 1 # clk $end
$var wire 10 8" d [9:0] $end
$var wire 1 ( w $end
$var parameter 10 9" INIT $end
$var reg 10 :" q [9:0] $end
$upscope $end
$upscope $end
$upscope $end
$enddefinitions $end
$comment Show the parameter values. $end
$dumpall
b1111111111 9"
b1001 /"
b1000 *"
b111 %"
b110 ~
b101 y
b100 t
b11 o
b10 j
b1 e
b1001 Y
b1000 T
b111 O
b110 J
b101 E
b100 @
b11 ;
b10 6
b1 1
$end
#0
$dumpvars
b1111111111 :"
b1111111110 8"
07"
16"
15"
14"
03"
12"
11"
10"
0."
1-"
1,"
1+"
0)"
1("
1'"
1&"
0$"
1#"
1""
1!"
0}
1|
1{
1z
0x
1w
1v
1u
0s
1r
1q
1p
0n
1m
1l
1k
0i
1h
1g
1f
b1111111111 d
b1111111111 c
b0 b
1a
1`
0_
0^
0]
1\
1[
0Z
0X
1W
1V
0U
0S
1R
1Q
0P
0N
1M
1L
0K
0I
1H
1G
0F
0D
1C
1B
0A
0?
1>
1=
0<
0:
19
18
07
05
14
13
02
b1111111111 0
b0 /
b1111111110 .
b1111111111 -
0,
b1111111110 +
1*
b0 )
1(
0'
0&
1%
0$
0#
b1111111111 "
0!
$end
#1
0*
13"
00"
01"
1."
0+"
0,"
1)"
0&"
0'"
1$"
0!"
0""
1}
0z
0{
1x
0u
0v
1s
0p
0q
1n
0k
0l
03
1i
0f
15
0g
b1111111101 8"
b1 /
1^
b1111111111 )
b1111111111 b
17"
b0 c
04"
b1111111101 +
b1111111101 .
1_
06"
0`
b1111111110 "
b1111111110 -
b1111111110 0
b1111111110 d
b1111111110 :"
1#
#2
0#
#3
18
05
0:
1g
0^
b1111111100 8"
b0 /
02
07"
b1 c
14"
b1111111110 )
b1111111110 b
1i
0_
b1111111100 +
b1111111100 .
03
16"
0h
1`
04
b1111111101 "
b1111111101 -
b1111111101 0
b1111111101 d
b1111111101 :"
1#
#4
0#
#5
08
1:
13
12
0i
15
0g
b1111111011 8"
b11 /
1^
b1111111101 )
b1111111101 b
17"
b0 c
04"
b1111111011 +
b1111111011 .
1_
06"
0`
b1111111100 "
b1111111100 -
b1111111100 0
b1111111100 d
b1111111100 :"
1#
#6
0#
#7
1l
1=
1f
05
0?
0:
1g
0^
07
b1111111010 8"
b0 /
02
07"
b11 c
14"
1n
b1111111100 )
b1111111100 b
0i
0_
08
b1111111010 +
b1111111010 .
13
16"
0m
1h
1`
09
14
b1111111011 "
b1111111011 -
b1111111011 0
b1111111011 d
b1111111011 :"
1#
#8
0#
#9
0n
0l
03
1i
0f
15
0g
b1111111001 8"
b1 /
1^
b1111111011 )
b1111111011 b
17"
b0 c
04"
b1111111001 +
b1111111001 .
1_
06"
0`
b1111111010 "
b1111111010 -
b1111111010 0
b1111111010 d
b1111111010 :"
1#
#10
0#
#11
1=
0?
08
07
05
0:
1g
0^
b1111111000 8"
b0 /
02
07"
b1 c
14"
b1111111010 )
b1111111010 b
1i
0_
b1111111000 +
b1111111000 .
03
16"
0h
1`
04
b1111111001 "
b1111111001 -
b1111111001 0
b1111111001 d
b1111111001 :"
1#
#12
0#
#13
0=
1?
18
17
1:
13
12
0i
15
0g
b1111110111 8"
b111 /
1^
b1111111001 )
b1111111001 b
17"
b0 c
04"
b1111110111 +
b1111110111 .
1_
06"
0`
b1111111000 "
b1111111000 -
b1111111000 0
b1111111000 d
b1111111000 :"
1#
#14
0#
#15
1=
0?
08
07
0:
03
02
1i
05
1g
b0 /
0^
b1111111010 )
b1111111010 b
07"
b1 c
14"
b1111111000 +
b1111111000 .
0_
16"
1`
b1111111001 "
b1111111001 -
b1111111001 0
b1111111001 d
b1111111001 :"
b1111111010 8"
1#
0%
1$
#16
0#
#17
0n
15
0g
b1111111011 8"
0l
b1 /
1^
17"
04"
b1111111011 )
b1111111011 b
1i
b0 c
0f
1_
b1111111001 +
b1111111001 .
03
06"
1h
0`
14
b1111111010 "
b1111111010 -
b1111111010 0
b1111111010 d
b1111111010 :"
1#
#18
0#
#19
1n
1l
13
0i
1f
05
b1111111100 8"
1g
b0 /
0^
b1111111100 )
b1111111100 b
07"
b11 c
14"
b1111111010 +
b1111111010 .
0_
16"
1`
b1111111011 "
b1111111011 -
b1111111011 0
b1111111011 d
b1111111011 :"
1#
#20
0#
#21
0!
0&
0*
13"
00"
01"
1."
0+"
0,"
1)"
0&"
0'"
1$"
0!"
0""
1}
0z
0{
1x
0u
1:
0v
12
1s
0p
15
0g
0q
b1111111101 8"
0l
b11 /
1^
17"
04"
1n
0k
b1111111101 )
b1111111101 b
0i
b0 c
0f
1_
08
b1111111011 +
b1111111011 .
13
06"
1m
0h
0`
19
04
b1111111100 "
b1111111100 -
b1111111100 0
b1111111100 d
b1111111100 :"
1#
#22
0#
#23
18
0:
03
02
1i
05
b1111111110 8"
1g
b0 /
0^
b1111111110 )
b1111111110 b
07"
b1 c
14"
b1111111100 +
b1111111100 .
0_
16"
1`
b1111111101 "
b1111111101 -
b1111111101 0
b1111111101 d
b1111111101 :"
1#
#24
0#
#25
08
1:
13
12
0i
15
0g
b11 /
1^
b1111111101 )
b1111111101 b
17"
b0 c
04"
b1111111011 +
b1111111011 .
1_
06"
0`
b1111111100 "
b1111111100 -
b1111111100 0
b1111111100 d
b1111111100 :"
b1111111011 8"
1#
0$
1%
#26
0#
#27
1l
1=
1f
05
0?
0:
1g
0^
07
b1111111010 8"
b0 /
02
07"
b11 c
14"
1n
b1111111100 )
b1111111100 b
0i
0_
08
b1111111010 +
b1111111010 .
13
16"
0m
1h
1`
09
14
b1111111011 "
b1111111011 -
b1111111011 0
b1111111011 d
b1111111011 :"
1#
#28
0#
#29
0n
0l
03
1i
0f
15
0g
b1111111001 8"
b1 /
1^
b1111111011 )
b1111111011 b
17"
b0 c
04"
b1111111001 +
b1111111001 .
1_
06"
0`
b1111111010 "
b1111111010 -
b1111111010 0
b1111111010 d
b1111111010 :"
1#
#30
0#
#31
1=
0?
08
07
05
0:
1g
0^
b1111111000 8"
b0 /
02
07"
b1 c
14"
b1111111010 )
b1111111010 b
1i
0_
b1111111000 +
b1111111000 .
03
16"
0h
1`
04
b1111111001 "
b1111111001 -
b1111111001 0
b1111111001 d
b1111111001 :"
1#
#32
0#
#33
0=
1?
18
17
1:
13
12
0i
15
0g
b1111110111 8"
b111 /
1^
b1111111001 )
b1111111001 b
17"
b0 c
04"
b1111110111 +
b1111110111 .
1_
06"
0`
b1111111000 "
b1111111000 -
b1111111000 0
b1111111000 d
b1111111000 :"
1#
#34
0#
#35
1q
1k
1l
1B
1f
05
0D
0?
0:
1g
0^
0<
07
b1111110110 8"
b0 /
02
07"
b111 c
14"
1s
0n
b1111111000 )
b1111111000 b
0i
0_
0=
18
b1111110110 +
b1111110110 .
13
16"
0r
1m
1h
1`
0>
19
14
b1111110111 "
b1111110111 -
b1111110111 0
b1111110111 d
b1111110111 :"
1#
#36
0#
#37
0s
0q
1n
0k
0l
03
1i
0f
15
0g
b1111110101 8"
b1 /
1^
b1111110111 )
b1111110111 b
17"
b0 c
04"
b1111110101 +
b1111110101 .
1_
06"
0`
b1111110110 "
b1111110110 -
b1111110110 0
b1111110110 d
b1111110110 :"
1#
#38
0#
#39
18
05
0:
1g
0^
b1111110100 8"
b0 /
02
07"
b1 c
14"
b1111110110 )
b1111110110 b
1i
0_
b1111110100 +
b1111110100 .
03
16"
0h
1`
04
b1111110101 "
b1111110101 -
b1111110101 0
b1111110101 d
b1111110101 :"
1#
#40
0#
#41
08
1:
13
12
0i
15
0g
b1111110011 8"
b11 /
1^
b1111110101 )
b1111110101 b
17"
b0 c
04"
b1111110011 +
b1111110011 .
1_
06"
0`
b1111110100 "
b1111110100 -
b1111110100 0
b1111110100 d
b1111110100 :"
1#
#42
0#
#43
1B
0D
1l
0=
0<
1f
05
0?
0:
1g
0^
07
b1111110010 8"
b0 /
02
07"
b11 c
14"
1n
b1111110100 )
b1111110100 b
0i
0_
08
b1111110010 +
b1111110010 .
13
16"
0m
1h
1`
09
14
b1111110011 "
b1111110011 -
b1111110011 0
b1111110011 d
b1111110011 :"
1#
#44
0#
#45
0n
0l
03
1i
0f
15
0g
b1111110001 8"
b1 /
1^
b1111110011 )
b1111110011 b
17"
b0 c
04"
b1111110001 +
b1111110001 .
1_
06"
0`
b1111110010 "
b1111110010 -
b1111110010 0
b1111110010 d
b1111110010 :"
1#
#46
0#
#47
1B
0D
0=
0<
0?
08
07
05
0:
1g
0^
b1111110000 8"
b0 /
02
07"
b1 c
14"
b1111110010 )
b1111110010 b
1i
0_
b1111110000 +
b1111110000 .
03
16"
0h
1`
04
b1111110001 "
b1111110001 -
b1111110001 0
b1111110001 d
b1111110001 :"
1#
#48
0#
#49
0B
1D
1=
1<
1?
18
17
1:
13
12
0i
15
0g
b1111101111 8"
b1111 /
1^
b1111110001 )
b1111110001 b
17"
b0 c
04"
b1111101111 +
b1111101111 .
1_
06"
0`
b1111110000 "
b1111110000 -
b1111110000 0
b1111110000 d
b1111110000 :"
1#
#50
b1111110001 8"
0#
1$
0%
#51
1B
0D
0=
0<
0?
08
07
0:
03
02
1i
05
b1111110010 8"
1g
b0 /
0^
b1111110010 )
b1111110010 b
07"
b1 c
14"
b1111110000 +
b1111110000 .
0_
16"
1`
b1111110001 "
b1111110001 -
b1111110001 0
b1111110001 d
b1111110001 :"
1#
#52
0#
#53
0n
15
0g
b1111110011 8"
0l
b1 /
1^
17"
04"
b1111110011 )
b1111110011 b
1i
b0 c
0f
1_
b1111110001 +
b1111110001 .
03
06"
1h
0`
14
b1111110010 "
b1111110010 -
b1111110010 0
b1111110010 d
b1111110010 :"
1#
#54
0#
#55
1n
1l
13
0i
1f
05
b1111110100 8"
1g
b0 /
0^
b1111110100 )
b1111110100 b
07"
b11 c
14"
b1111110010 +
b1111110010 .
0_
16"
1`
b1111110011 "
b1111110011 -
b1111110011 0
b1111110011 d
b1111110011 :"
1#
#56
0#
#57
1:
12
0s
15
0g
0q
b1111110101 8"
0l
b11 /
1^
17"
04"
1n
0k
b1111110101 )
b1111110101 b
0i
b0 c
0f
1_
08
b1111110011 +
b1111110011 .
13
06"
1m
0h
0`
19
04
b1111110100 "
b1111110100 -
b1111110100 0
b1111110100 d
b1111110100 :"
1#
#58
0#
#59
18
0:
03
02
1i
05
b1111110110 8"
1g
b0 /
0^
b1111110110 )
b1111110110 b
07"
b1 c
14"
b1111110100 +
b1111110100 .
0_
16"
1`
b1111110101 "
b1111110101 -
b1111110101 0
b1111110101 d
b1111110101 :"
1#
#60
0#
#61
0s
0q
1n
0k
15
0g
b1111110111 8"
0l
b1 /
1^
17"
04"
b1111110111 )
b1111110111 b
1i
b0 c
0f
1_
b1111110101 +
b1111110101 .
03
06"
1h
0`
14
b1111110110 "
b1111110110 -
b1111110110 0
b1111110110 d
b1111110110 :"
1#
#62
0#
#63
1s
1q
0n
1k
1l
13
0i
1f
05
b1111111000 8"
1g
b0 /
0^
b1111111000 )
b1111111000 b
07"
b111 c
14"
b1111110110 +
b1111110110 .
0_
16"
1`
b1111110111 "
b1111110111 -
b1111110111 0
b1111110111 d
b1111110111 :"
1#
#64
0#
#65
0!
0&
0*
13"
00"
01"
1."
0+"
0,"
1)"
0&"
0'"
1$"
0!"
1?
0""
17
1}
0z
1:
0{
12
1x
0u
15
0g
0v
0q
b1111111001 8"
0l
b111 /
1^
17"
04"
1s
0p
0n
0k
b1111111001 )
b1111111001 b
0i
b0 c
0f
1_
0=
18
b1111110111 +
b1111110111 .
13
06"
1r
0m
0h
0`
1>
09
04
b1111111000 "
b1111111000 -
b1111111000 0
b1111111000 d
b1111111000 :"
1#
#66
0#
#67
1=
0?
08
07
0:
03
02
1i
05
b1111111010 8"
1g
b0 /
0^
b1111111010 )
b1111111010 b
07"
b1 c
14"
b1111111000 +
b1111111000 .
0_
16"
1`
b1111111001 "
b1111111001 -
b1111111001 0
b1111111001 d
b1111111001 :"
1#
#68
0#
#69
0n
15
0g
b1111111011 8"
0l
b1 /
1^
17"
04"
b1111111011 )
b1111111011 b
1i
b0 c
0f
1_
b1111111001 +
b1111111001 .
03
06"
1h
0`
14
b1111111010 "
b1111111010 -
b1111111010 0
b1111111010 d
b1111111010 :"
1#
#70
0#
#71
1n
1l
13
0i
1f
05
b1111111100 8"
1g
b0 /
0^
b1111111100 )
b1111111100 b
07"
b11 c
14"
b1111111010 +
b1111111010 .
0_
16"
1`
b1111111011 "
b1111111011 -
b1111111011 0
b1111111011 d
b1111111011 :"
1#
#72
0#
#73
0!
0&
0*
13"
00"
01"
1."
0+"
0,"
1)"
0&"
0'"
1$"
0!"
0""
1}
0z
0{
1x
0u
1:
0v
12
1s
0p
15
0g
0q
b1111111101 8"
0l
b11 /
1^
17"
04"
1n
0k
b1111111101 )
b1111111101 b
0i
b0 c
0f
1_
08
b1111111011 +
b1111111011 .
13
06"
1m
0h
0`
19
04
b1111111100 "
b1111111100 -
b1111111100 0
b1111111100 d
b1111111100 :"
1#
#74
0#
#75
18
0:
03
02
1i
05
b1111111110 8"
1g
b0 /
0^
b1111111110 )
b1111111110 b
07"
b1 c
14"
b1111111100 +
b1111111100 .
0_
16"
1`
b1111111101 "
b1111111101 -
b1111111101 0
b1111111101 d
b1111111101 :"
1#
#76
0#
#77
0!
0&
0*
13"
00"
01"
1."
0+"
0,"
1)"
0&"
0'"
1$"
0!"
0""
1}
0z
0{
1x
0u
0v
1s
0p
0q
1n
0k
15
0g
b1111111111 8"
0l
b1 /
1^
17"
04"
b1111111111 )
b1111111111 b
1i
b0 c
0f
1_
b1111111101 +
b1111111101 .
03
06"
1h
0`
14
b1111111110 "
b1111111110 -
b1111111110 0
b1111111110 d
b1111111110 :"
1#
#78
0#
#79
1!
1&
1*
03"
10"
11"
0."
1+"
1,"
0)"
1&"
1'"
0$"
1!"
1""
0}
1z
1{
0x
1u
1v
0s
1p
1q
0n
1k
1l
13
0i
1f
05
b0 8"
1g
b0 /
0^
b0 )
b0 b
07"
b1111111111 c
14"
b1111111110 +
b1111111110 .
0_
16"
1`
b1111111111 "
b1111111111 -
b1111111111 0
b1111111111 d
b1111111111 :"
1#
#80
0#
#81
1,
1Z
1]
1U
1X
1P
1S
1K
1N
1F
1I
1A
1D
1<
1?
17
1:
0!
12
0&
15
0g
0*
01"
0,"
0'"
0""
0{
0v
0q
b1 8"
0l
b1111111111 /
1^
17"
04"
03"
00"
0."
0+"
0)"
0&"
0$"
0!"
0}
0z
0x
0u
0s
0p
0n
0k
b1 )
b1 b
0i
b0 c
0f
1_
1[
1V
1Q
1L
1G
1B
1=
18
b1111111111 +
b1111111111 .
13
06"
02"
0-"
0("
0#"
0|
0w
0r
0m
0h
0`
0\
0W
0R
0M
0H
0C
0>
09
04
b0 "
b0 -
b0 0
b0 d
b0 :"
1#
#82
0#
#83
0,
0[
0Z
0]
0V
0U
0X
0Q
0P
0S
0L
0K
0N
0G
0F
0I
0B
0A
0D
0=
0<
0?
08
07
0:
03
02
1i
05
b10 8"
1g
b0 /
0^
b10 )
b10 b
07"
b1 c
14"
b0 +
b0 .
0_
16"
1`
b1 "
b1 -
b1 0
b1 d
b1 :"
1#
#84
0#
#85
0n
15
0g
b11 8"
0l
b1 /
1^
17"
04"
b11 )
b11 b
1i
b0 c
0f
1_
b1 +
b1 .
03
06"
1h
0`
14
b10 "
b10 -
b10 0
b10 d
b10 :"
1#
#86
0#
#87
1n
1l
13
0i
1f
05
b100 8"
1g
b0 /
0^
b100 )
b100 b
07"
b11 c
14"
b10 +
b10 .
0_
16"
1`
b11 "
b11 -
b11 0
b11 d
b11 :"
1#
#88
0#
#89
1:
12
0s
15
0g
0q
b101 8"
0l
b11 /
1^
17"
04"
1n
0k
b101 )
b101 b
0i
b0 c
0f
1_
08
b11 +
b11 .
13
06"
1m
0h
0`
19
04
b100 "
b100 -
b100 0
b100 d
b100 :"
1#
