Verilog/Memory/ram.v
module ram(
    input [9:0] addr,
    input [19:0] write,
    input clk, str, ld,
    output reg [19:0] read);

    reg [19:0] mem [0:1023];

    integer i;
    initial begin
        for(i = 0; i < 1024; i = i + 1) begin
            mem[i] = 20'd0;
        end
    end

    always @(posedge clk) begin
        if(str)
            mem[addr] <= write;
    end

    always @(*) begin
        read = ld ? mem[addr] : 20'dx;
    end
endmodule

Verilog/Memory/ram_tb.v
`timescale 1ns/1ns
`include "Memory/ram.v"

module ram_tb;
    reg [9:0] addr;
    reg [19:0] write;
    reg clk, str, ld;
    wire [19:0] read;

    ram mem(addr, write, clk, str, ld, read);

    initial begin
        clk = 0;
        #10
        forever #5 clk = ~clk;
    end

    initial begin
        $dumpfile("ram_tb.vcd");
        $dumpvars(0,ram_tb);

        ld = 1;
        addr = 0; write = 101; str = 0;
        #10
        str = 1;
        #10

        ld = 0;
        #10

        ld = 1;
        addr = 1; write = 202;
        #10

        addr = 2; write = 303;
        #10

        addr = 3; write = 404;
        #10

        addr = 4; write = 505;
        #10

        $finish;
    end
endmodule

Verilog/Memory/ram_tb.vcd
$date
	Fri Jan 06 21:37:16 2023
$end
$version
	Icarus Verilog
$end
$timescale
	1ns
$end
$scope module ram_tb $end
$var wire 20 ! read [19:0] $end
$var reg 10 " addr [9:0] $end
$var reg 1 # clk $end
$var reg 1 $ ld $end
$var reg 1 % str $end
$var reg 20 & write [19:0] $end
$scope module mem $end
$var wire 10 ' addr [9:0] $end
$var wire 1 # clk $end
$var wire 1 $ ld $end
$var wire 1 % str $end
$var wire 20 ( write [19:0] $end
$var reg 20 ) read [19:0] $end
$var integer 32 * i [31:0] $end
$upscope $end
$upscope $end
$enddefinitions $end
$comment Show the parameter values. $end
$dumpall
$end
#0
$dumpvars
b10000000000 *
b0 )
b1100101 (
b0 '
b1100101 &
0%
1$
0#
b0 "
b0 !
$end
#10
1%
#15
b1100101 !
b1100101 )
1#
#20
bx !
bx )
0#
0$
#25
1#
#30
b0 !
b0 )
0#
b11001010 &
b11001010 (
b1 "
b1 '
1$
#35
b11001010 !
b11001010 )
1#
#40
b0 !
b0 )
0#
b100101111 &
b100101111 (
b10 "
b10 '
#45
b100101111 !
b100101111 )
1#
#50
b0 !
b0 )
0#
b110010100 &
b110010100 (
b11 "
b11 '
#55
b110010100 !
b110010100 )
1#
#60
b0 !
b0 )
0#
b111111001 &
b111111001 (
b100 "
b100 '
#65
b111111001 !
b111111001 )
1#
