Verilog/Latches/Rising Edge Triggered D Flip-Flop/rising_edge_triggered_d_flipflop.v
module rising_edge_triggered_d_flipflop(
    input d, w, clk,
    output reg q);

    initial begin
        q = 0;
    end

    always @(posedge clk) begin
        if(w)
            q <= d;
    end
endmodule

Verilog/Registers/10 Bit Register/ten_bit_register.v
`include "Latches/Rising Edge Triggered D Flip-Flop/rising_edge_triggered_d_flipflop.v"

module ten_bit_register(
    input [9:0] d,
    input clk, w,
    output [9:0] q);

    genvar i;

    generate
        for(i = 0; i < 10; i = i + 1) begin
            rising_edge_triggered_d_flipflop flipflopi(d[i], w, clk, q[i]);
        end
    endgenerate
endmodule

Verilog/Registers/10 Bit Register/ten_bit_register_tb.v
`timescale 1ns/1ns
`include "Registers/10 Bit Register/ten_bit_register.v"

module ten_bit_register_tb;
    reg [9:0] d;
    reg clk, w;
    wire [9:0] q;

    ten_bit_register regs(d, clk, w, q);

    initial begin
        clk = 0;
        forever #1 clk = ~clk;
    end

    initial begin
        $dumpfile("ten_bit_register_tb.vcd");
        $dumpvars(0, ten_bit_register_tb);

        d = 10'd45; w = 1;
        #10

        d = 10'd54; w = 1;
        #10

        d = 10'd100; w = 0;
        #10

        d = 10'd101; w = 1;
        #10

        d = 10'd105; w = 1;
        #10

        d = 10'd0; w = 0;
        #10

        d = 10'd0; w = 1;
        #10

        $finish;
    end

endmodule

Verilog/Registers/10 Bit Register/ten_bit_register_tb.vcd
$date
	Fri Jan 06 22:22:02 2023
$end
$version
	Icarus Verilog
$end
$timescale
	1ns
$end
$scope module ten_bit_register_tb $end
$var wire 10 ! q [9:0] $end
$var reg 1 " clk $end
$var reg 10 # d [9:0] $end
$var reg 1 $ w $end
$scope module regs $end
$var wire 1 " clk $end
$var wire 10 % d [9:0] $end
$var wire 1 $ w $end
$var wire 10 & q [9:0] $end
$scope begin genblk1[0] $end
$var parameter 2 ' i $end
$scope module flipflopi $end
$var wire 1 " clk $end
$var wire 1 ( d $end
$var wire 1 $ w $end
$var reg 1 ) q $end
$upscope $end
$upscope $end
$scope begin genblk1[1] $end
$var parameter 2 * i $end
$scope module flipflopi $end
$var wire 1 " clk $end
$var wire 1 + d $end
$var wire 1 $ w $end
$var reg 1 , q $end
$upscope $end
$upscope $end
$scope begin genblk1[2] $end
$var parameter 3 - i $end
$scope module flipflopi $end
$var wire 1 " clk $end
$var wire 1 . d $end
$var wire 1 $ w $end
$var reg 1 / q $end
$upscope $end
$upscope $end
$scope begin genblk1[3] $end
$var parameter 3 0 i $end
$scope module flipflopi $end
$var wire 1 " clk $end
$var wire 1 1 d $end
$var wire 1 $ w $end
$var reg 1 2 q $end
$upscope $end
$upscope $end
$scope begin genblk1[4] $end
$var parameter 4 3 i $end
$scope module flipflopi $end
$var wire 1 " clk $end
$var wire 1 4 d $end
$var wire 1 $ w $end
$var reg 1 5 q $end
$upscope $end
$upscope $end
$scope begin genblk1[5] $end
$var parameter 4 6 i $end
$scope module flipflopi $end
$var wire 1 " clk $end
$var wire 1 7 d $end
$var wire 1 $ w $end
$var reg 1 8 q $end
$upscope $end
$upscope $end
$scope begin genblk1[6] $end
$var parameter 4 9 i $end
$scope module flipflopi $end
$var wire 1 " clk $end
$var wire 1 : d $end
$var wire 1 $ w $end
$var reg 1 ; q $end
$upscope $end
$upscope $end
$scope begin genblk1[7] $end
$var parameter 4 < i $end
$scope module flipflopi $end
$var wire 1 " clk $end
$var wire 1 = d $end
$var wire 1 $ w $end
$var reg 1 > q $end
$upscope $end
$upscope $end
$scope begin genblk1[8] $end
$var parameter 5 ? i $end
$scope module flipflopi $end
$var wire 1 " clk $end
$var wire 1 @ d $end
$var wire 1 $ w $end
$var reg 1 A q $end
$upscope $end
$upscope $end
$scope begin genblk1[9] $end
$var parameter 5 B i $end
$scope module flipflopi $end
$var wire 1 " clk $end
$var wire 1 C d $end
$var wire 1 $ w $end
$var reg 1 D q $end
$upscope $end
$upscope $end
$upscope $end
$upscope $end
$enddefinitions $end
$comment Show the parameter values. $end
$dumpall
b1001 B
b1000 ?
b111 <
b110 9
b101 6
b100 3
b11 0
b10 -
b1 *
b0 '
$end
#0
$dumpvars
0D
0C
0A
0@
0>
0=
0;
0:
08
17
05
04
02
11
0/
1.
0,
0+
0)
1(
b0 &
b101101 %
1$
b101101 #
0"
b0 !
$end
#1
1)
1/
12
b101101 !
b101101 &
18
1"
#2
0"
#3
1"
#4
0"
#5
1"
#6
0"
#7
1"
#8
0"
#9
1"
#10
0(
1+
01
14
0"
b110110 #
b110110 %
#11
15
02
1,
b110110 !
b110110 &
0)
1"
#12
0"
#13
1"
#14
0"
#15
1"
#16
0"
#17
1"
#18
0"
#19
1"
#20
0+
04
1:
0"
0$
b1100100 #
b1100100 %
#21
1"
#22
0"
#23
1"
#24
0"
#25
1"
#26
0"
#27
1"
#28
0"
#29
1"
#30
1(
0"
1$
b1100101 #
b1100101 %
#31
1;
05
0,
b1100101 !
b1100101 &
1)
1"
#32
0"
#33
1"
#34
0"
#35
1"
#36
0"
#37
1"
#38
0"
#39
1"
#40
0.
11
0"
b1101001 #
b1101001 %
#41
0/
b1101001 !
b1101001 &
12
1"
#42
0"
#43
1"
#44
0"
#45
1"
#46
0"
#47
1"
#48
0"
#49
1"
#50
0(
01
07
0:
0"
0$
b0 #
b0 %
#51
1"
#52
0"
#53
1"
#54
0"
#55
1"
#56
0"
#57
1"
#58
0"
#59
1"
#60
0"
1$
#61
0)
02
08
b0 !
b0 &
0;
1"
