Verilog/Control Unit/Next State/next_state.v
module next_state(
    input alu, ld, st, push, pop, jump, be, s2, s1, s0,
    output s2_n, s1_n, s0_n);

    assign s0_n = (~s2) & (~s0) & ((~s1) | (s1 & (alu | jump | be)));
    assign s1_n = (~s2) & (((~s1) & s0) | (((~s0) & s1) & (alu | jump | be)));
    assign s2_n = (~s2) & s1 & (s0 | ((~s0) & (ld | st | push | pop)));
endmodule

Verilog/Control Unit/Next State/next_state_tb.v
`include "Control Unit/Next State/next_state.v"

module next_state_tb;
    reg alu, ld, st, push, pop, jump, be, s2, s1, s0;
    wire s2_n, s1_n, s0_n;

    next_state next(alu, ld, st, push, pop, jump, be, s2, s1, s0, s2_n, s1_n, s0_n);

    initial begin
        $dumpfile("next_state_tb.vcd");
        $dumpvars(0, next_state_tb);

        alu = 0;
        ld = 0;
        st = 0;
        push = 0;
        pop = 0;
        jump = 0;
        be = 0;
        s2 = 0;
        s1 = 0;
        s0 = 0;

        #5

        alu = 1;
        #5

        alu = 0; ld = 1;
        #5

        ld = 0; st = 1;
        #5

        st = 0; push = 1;
        #5

        push = 0; pop = 1;
        #5

        pop = 0; jump = 1;
        #5

        jump = 0; be = 1;
        #5

        s0 = 1;
        #5

        be = 0; jump = 1;
        #5

        jump = 0; pop = 1;
        #5

        pop = 0; push = 1;
        #5

        push = 0; st = 1;
        #5

        st = 0; ld = 1;
        #5

        ld = 0; alu = 1;
        #5

        s0 = 0; s1 = 1;
        #5

        alu = 0; ld = 1;
        #5

        ld = 0; st = 1;
        #5

        st = 0; push = 1;
        #5

        push = 0; pop = 1;
        #5

        pop = 0; jump = 1;
        #5

        jump = 0; be = 1;
        #5

        s0 = 1;
        #5

        be = 0; jump = 1;
        #5

        jump = 0; pop = 1;
        #5

        pop = 0; push = 1;
        #5

        push = 0; st = 1;
        #5

        st = 0; ld = 1;
        #5

        ld = 0; alu = 1;
        #5

        s0 = 0; s1 = 0; s2 = 1;
        #5

        alu = 0; ld = 1;
        #5

        ld = 0; st = 1;
        #5

        st = 0; push = 1;
        #5

        push = 0; pop = 1;
        #5

        pop = 0; jump = 1;
        #5

        jump = 0; be = 1;
        #5
        
        $finish;
    end
endmodule

Verilog/Control Unit/Next State/next_state_tb.vcd
$date
	Sat Jan 07 17:35:49 2023
$end
$version
	Icarus Verilog
$end
$timescale
	1s
$end
$scope module next_state_tb $end
$var wire 1 ! s2_n $end
$var wire 1 " s1_n $end
$var wire 1 # s0_n $end
$var reg 1 $ alu $end
$var reg 1 % be $end
$var reg 1 & jump $end
$var reg 1 ' ld $end
$var reg 1 ( pop $end
$var reg 1 ) push $end
$var reg 1 * s0 $end
$var reg 1 + s1 $end
$var reg 1 , s2 $end
$var reg 1 - st $end
$scope module next $end
$var wire 1 $ alu $end
$var wire 1 % be $end
$var wire 1 & jump $end
$var wire 1 ' ld $end
$var wire 1 ( pop $end
$var wire 1 ) push $end
$var wire 1 * s0 $end
$var wire 1 # s0_n $end
$var wire 1 + s1 $end
$var wire 1 " s1_n $end
$var wire 1 , s2 $end
$var wire 1 ! s2_n $end
$var wire 1 - st $end
$upscope $end
$upscope $end
$enddefinitions $end
$comment Show the parameter values. $end
$dumpall
$end
#0
$dumpvars
0-
0,
0+
0*
0)
0(
0'
0&
0%
0$
1#
0"
0!
$end
#5
1$
#10
1'
0$
#15
1-
0'
#20
1)
0-
#25
1(
0)
#30
1&
0(
#35
1%
0&
#40
0#
1"
1*
#45
1&
0%
#50
1(
0&
#55
1)
0(
#60
1-
0)
#65
1'
0-
#70
1$
0'
#75
1#
1"
1+
0*
#80
1!
0#
0"
1'
0$
#85
1-
0'
#90
1)
0-
#95
1(
0)
#100
1#
1"
0!
1&
0(
#105
1%
0&
#110
0"
0#
1!
1*
#115
1&
0%
#120
1(
0&
#125
1)
0(
#130
1-
0)
#135
1'
0-
#140
1$
0'
#145
0!
1,
0+
0*
#150
1'
0$
#155
1-
0'
#160
1)
0-
#165
1(
0)
#170
1&
0(
#175
1%
0&
