Verilog/Latches/Rising Edge Triggered D Flip-Flop/rising_edge_triggered_d_flipflop.v
module rising_edge_triggered_d_flipflop(
    input d, w, clk,
    output reg q);

    initial begin
        q = 0;
    end

    always @(posedge clk) begin
        if(w)
            q <= d;
    end
endmodule

Verilog/Latches/Rising Edge Triggered D Flip-Flop/rising_edge_triggered_d_flipflop_tb.v
`timescale 1ns/1ns
`include "Latches/Rising Edge Triggered D Flip-Flop/rising_edge_triggered_d_flipflop.v"

module rising_edge_triggered_d_flipflop_tb;
    reg d, w, clk;
    wire q;

    rising_edge_triggered_d_flipflop flipflop(d, w, clk, q);

    initial begin
        clk = 0;
        forever #1 clk = ~clk;
    end

    initial begin
        $dumpfile("rising_edge_triggered_d_flipflop_tb.vcd");
        $dumpvars(0, rising_edge_triggered_d_flipflop_tb);

        d = 1; w = 0;
        #10;

        d = 1; w = 0;
        #10;

        d = 1; w = 1;
        #10;

        d = 0; w = 1;
        #10;

        d = 0; w = 1;
        #10;

        d = 1; w = 1;
        #10;

        d = 0; w = 0;
        #10;

        d = 0; w = 0;
        #10;

        d = 1; w = 1;
        #10;

        d = 1; w = 1;
        #10;

        d = 1; w = 1;
        #10

        $finish;
    end
endmodule

Verilog/Latches/Rising Edge Triggered D Flip-Flop/rising_edge_triggered_d_flipflop_tb.vcd
$date
	Fri Jan 06 22:15:39 2023
$end
$version
	Icarus Verilog
$end
$timescale
	1ns
$end
$scope module rising_edge_triggered_d_flipflop_tb $end
$var wire 1 ! q $end
$var reg 1 " clk $end
$var reg 1 # d $end
$var reg 1 $ w $end
$scope module flipflop $end
$var wire 1 " clk $end
$var wire 1 # d $end
$var wire 1 $ w $end
$var reg 1 ! q $end
$upscope $end
$upscope $end
$enddefinitions $end
$comment Show the parameter values. $end
$dumpall
$end
#0
$dumpvars
0$
1#
0"
0!
$end
#1
1"
#2
0"
#3
1"
#4
0"
#5
1"
#6
0"
#7
1"
#8
0"
#9
1"
#10
0"
#11
1"
#12
0"
#13
1"
#14
0"
#15
1"
#16
0"
#17
1"
#18
0"
#19
1"
#20
0"
1$
#21
1!
1"
#22
0"
#23
1"
#24
0"
#25
1"
#26
0"
#27
1"
#28
0"
#29
1"
#30
0"
0#
#31
0!
1"
#32
0"
#33
1"
#34
0"
#35
1"
#36
0"
#37
1"
#38
0"
#39
1"
#40
0"
#41
1"
#42
0"
#43
1"
#44
0"
#45
1"
#46
0"
#47
1"
#48
0"
#49
1"
#50
0"
1#
#51
1!
1"
#52
0"
#53
1"
#54
0"
#55
1"
#56
0"
#57
1"
#58
0"
#59
1"
#60
0"
0$
0#
#61
1"
#62
0"
#63
1"
#64
0"
#65
1"
#66
0"
#67
1"
#68
0"
#69
1"
#70
0"
#71
1"
#72
0"
#73
1"
#74
0"
#75
1"
#76
0"
#77
1"
#78
0"
#79
1"
#80
0"
1$
1#
