Verilog/Control Unit/Next State/next_state.v
module next_state(
    input alu, ld, st, push, pop, jump, be, s2, s1, s0,
    output s2_n, s1_n, s0_n);

    assign s0_n = (~s2) & (~s0) & ((~s1) | (s1 & (alu | jump | be)));
    assign s1_n = (~s2) & (((~s1) & s0) | (((~s0) & s1) & (alu | jump | be)));
    assign s2_n = (~s2) & s1 & (s0 | ((~s0) & (ld | st | push | pop)));
endmodule

Verilog/Latches/Rising Edge Triggered D Flip-Flop/rising_edge_triggered_d_flipflop.v
`define RETDFF

module rising_edge_triggered_d_flipflop(
    input d, w, clk,
    output reg q);

    initial begin
        q = 0;
    end

    always @(posedge clk) begin
        if(w)
            q <= d;
    end
endmodule

Verilog/Control Unit/State Manager/state_manager.v
`ifndef RETDFF
`include "Latches/Rising Edge Triggered D Flip-Flop/rising_edge_triggered_d_flipflop.v"
`endif
`include "Control Unit/Next State/next_state.v"

module state_manager(
    input alu, ld, st, push, pop, jump, be, clk,
    output s2, s1, s0);

    wire s2_n, s1_n, s0_n;

    rising_edge_triggered_d_flipflop s2f(s2_n, 1'b1, clk, s2);
    rising_edge_triggered_d_flipflop s1f(s1_n, 1'b1, clk, s1);
    rising_edge_triggered_d_flipflop s0f(s0_n, 1'b1, clk, s0);

    next_state nextstate(alu, ld, st, push, pop, jump, be, s2, s1, s0, s2_n, s1_n, s0_n);
endmodule

Verilog/Control Unit/State Manager/state_manager_tb.v
`timescale 1ns/1ns
`include "Control Unit/State Manager/state_manager.v"

module state_manager_tb;
    reg alu, ld, st, push, pop, jump, be, clk;
    wire s2, s1, s0;

    state_manager manager(alu, ld, st, push, pop, jump, be, clk, s2, s1, s0);
    
    initial begin
        alu = 0;
        ld = 0;
        st = 0;
        push = 0;
        pop = 0;
        jump = 0;
        be = 0;
        clk = 0;

        forever #1 clk = ~clk;
    end

    initial begin
        $dumpfile("state_manager_tb.vcd");
        $dumpvars(0,state_manager_tb);

        alu = 1;
        #10

        alu = 0; ld = 1;
        #8

        ld = 0; st = 1;
        #8

        st = 0; push = 1;
        #8

        push = 0; pop = 1;
        #8

        pop = 0; jump = 1;
        #10

        jump = 0; be = 1;
        #10

        $finish;
    end
endmodule

Verilog/Control Unit/State Manager/state_manager_tb.vcd
$date
	Sun Jan 08 02:19:55 2023
$end
$version
	Icarus Verilog
$end
$timescale
	1ns
$end
$scope module state_manager_tb $end
$var wire 1 ! s2 $end
$var wire 1 " s1 $end
$var wire 1 # s0 $end
$var reg 1 $ alu $end
$var reg 1 % be $end
$var reg 1 & clk $end
$var reg 1 ' jump $end
$var reg 1 ( ld $end
$var reg 1 ) pop $end
$var reg 1 * push $end
$var reg 1 + st $end
$scope module manager $end
$var wire 1 $ alu $end
$var wire 1 % be $end
$var wire 1 & clk $end
$var wire 1 ' jump $end
$var wire 1 ( ld $end
$var wire 1 ) pop $end
$var wire 1 * push $end
$var wire 1 + st $end
$var wire 1 , s2_n $end
$var wire 1 ! s2 $end
$var wire 1 - s1_n $end
$var wire 1 " s1 $end
$var wire 1 . s0_n $end
$var wire 1 # s0 $end
$scope module nextstate $end
$var wire 1 $ alu $end
$var wire 1 % be $end
$var wire 1 ' jump $end
$var wire 1 ( ld $end
$var wire 1 ) pop $end
$var wire 1 * push $end
$var wire 1 . s0_n $end
$var wire 1 - s1_n $end
$var wire 1 , s2_n $end
$var wire 1 + st $end
$var wire 1 ! s2 $end
$var wire 1 " s1 $end
$var wire 1 # s0 $end
$upscope $end
$scope module s0f $end
$var wire 1 & clk $end
$var wire 1 . d $end
$var wire 1 / w $end
$var reg 1 # q $end
$upscope $end
$scope module s1f $end
$var wire 1 & clk $end
$var wire 1 - d $end
$var wire 1 0 w $end
$var reg 1 " q $end
$upscope $end
$scope module s2f $end
$var wire 1 & clk $end
$var wire 1 , d $end
$var wire 1 1 w $end
$var reg 1 ! q $end
$upscope $end
$upscope $end
$upscope $end
$enddefinitions $end
$comment Show the parameter values. $end
$dumpall
$end
#0
$dumpvars
11
10
1/
1.
0-
0,
0+
0*
0)
0(
0'
0&
0%
1$
0#
0"
0!
$end
#1
1-
0.
1#
1&
#2
0&
#3
1-
1.
0#
1"
1&
#4
0&
#5
0-
0.
1,
1#
1&
#6
0&
#7
0,
0#
0"
1!
1&
#8
0&
#9
1.
0!
1&
#10
0&
1(
0$
#11
1-
0.
1#
1&
#12
0&
#13
1,
0-
1"
0#
1&
#14
0&
#15
0,
0"
1!
1&
#16
0&
#17
1.
0!
1&
#18
0&
1+
0(
#19
1-
0.
1#
1&
#20
0&
#21
1,
0-
1"
0#
1&
#22
0&
#23
0,
0"
1!
1&
#24
0&
#25
1.
0!
1&
#26
0&
1*
0+
#27
1-
0.
1#
1&
#28
0&
#29
1,
0-
1"
0#
1&
#30
0&
#31
0,
0"
1!
1&
#32
0&
#33
1.
0!
1&
#34
0&
1)
0*
#35
1-
0.
1#
1&
#36
0&
#37
1,
0-
1"
0#
1&
#38
0&
#39
0,
0"
1!
1&
#40
0&
#41
1.
0!
1&
#42
0&
1'
0)
#43
1-
0.
1#
1&
#44
0&
#45
1-
1.
1"
0#
1&
#46
0&
#47
0-
0.
1,
1#
1&
#48
0&
#49
0,
1!
0"
0#
1&
#50
0&
#51
1.
0!
1&
#52
0&
1%
0'
#53
1-
0.
1#
1&
#54
0&
#55
1-
1.
0#
1"
1&
#56
0&
#57
0-
0.
1,
1#
1&
#58
0&
#59
0,
0#
0"
1!
1&
#60
0&
#61
1.
0!
1&
