Verilog/Adder/Half Adder/half_adder.v
module half_adder(i0, i1, s, cout);
    input i0, i1;
    output s, cout;

    xor x(s, i0, i1);
    and a(cout, i0, i1);
endmodule

Verilog/Adder/Full Adder/full_adder.v
`include "../Half Adder/half_adder.v"

module full_adder(i0, i1, cin, s, cout);
    input i0, i1, cin;
    output s, cout;

    wire s1, c1, c2;

    half_adder ha1(i0, i1, s1, c1);
    half_adder ha2(cin, s1, s, c2);

    or o(cout, c1, c2);
endmodule

Verilog/Adder/Full Adder/full_adder_tb.v
`include "full_adder.v"

module full_adder_tb;
    reg a, b, c;
    wire s, cout;

    full_adder fa(a, b, c, s, cout);

    initial begin
        $dumpfile("full_adder_tb.vcd");
        $dumpvars(0, full_adder_tb);

        a = 0; b = 0; c = 0;
        #1

        a = 0; b = 0; c = 1;
        #1

        a = 0; b = 1; c = 0;
        #1

        a = 1; b = 0; c = 0;
        #1

        a = 0; b = 1; c = 1;
        #1

        a = 1; b = 0; c = 1;
        #1

        a = 1; b = 1; c = 0;
        #1

        a = 1; b = 1; c = 1;
    end

endmodule

Verilog/Adder/Full Adder/full_adder_tb.vcd
$date
	Thu Jan 05 03:44:10 2023
$end
$version
	Icarus Verilog
$end
$timescale
	1s
$end
$scope module full_adder_tb $end
$var wire 1 ! s $end
$var wire 1 " cout $end
$var reg 1 # a $end
$var reg 1 $ b $end
$var reg 1 % c $end
$scope module fa $end
$var wire 1 % cin $end
$var wire 1 " cout $end
$var wire 1 # i0 $end
$var wire 1 $ i1 $end
$var wire 1 & s1 $end
$var wire 1 ! s $end
$var wire 1 ' c2 $end
$var wire 1 ( c1 $end
$scope module ha1 $end
$var wire 1 ( cout $end
$var wire 1 # i0 $end
$var wire 1 $ i1 $end
$var wire 1 & s $end
$upscope $end
$scope module ha2 $end
$var wire 1 ' cout $end
$var wire 1 % i0 $end
$var wire 1 & i1 $end
$var wire 1 ! s $end
$upscope $end
$upscope $end
$upscope $end
$enddefinitions $end
$comment Show the parameter values. $end
$dumpall
$end
#0
$dumpvars
0(
0'
0&
0%
0$
0#
0"
0!
$end
#1
1!
1%
#2
1&
0%
1$
#3
0$
1#
#4
1"
0!
1'
1%
1$
0#
#5
0$
1#
#6
0'
0&
1(
0%
1$
#7
1!
1%
