Verilog/Latches/Falling Edge Triggered D Flip-Flop/falling_edge_triggered_d_flipflop.v
module falling_edge_triggered_d_flipflop(
    input d, w, clk, reset,
    output reg q);

    always @(negedge clk or reset) begin
        if(reset & ~clk) begin
            q <= 0;
        end else if(w) begin
            q <= d;
        end
    end
endmodule

Verilog/Latches/Falling Edge Triggered D Flip-Flop/falling_edge_triggered_d_flipflop_tb.v
`timescale 1ns/1ns
`include "Latches/Falling Edge Triggered D Flip-Flop/falling_edge_triggered_d_flipflop.v"

module falling_edge_triggered_d_flipflop_tb;
    reg d, w, clk, reset;
    wire q;

    falling_edge_triggered_d_flipflop flipflop(d, w, clk, reset, q);

    initial begin
        clk = 0;
        reset = 1;
        #1
        reset = 0;
        forever #1 clk = ~clk;
    end

    initial begin
        $dumpfile("falling_edge_triggered_d_flipflop_tb.vcd");
        $dumpvars(0, falling_edge_triggered_d_flipflop_tb);

        d = 1; w = 0;
        #10;

        d = 1; w = 0;
        #10;

        d = 1; w = 1;
        #10;

        d = 0; w = 1;
        #10;

        d = 0; w = 1;
        #10;

        d = 1; w = 1; reset = 1;
        #10;

        d = 0; w = 0; reset = 0;
        #10;

        d = 0; w = 0;
        #10;

        d = 1; w = 1;
        #10;

        d = 1; w = 1; reset = 1;
        #10;

        d = 1; w = 1; reset = 0;

        $finish;
    end
endmodule

Verilog/Latches/Falling Edge Triggered D Flip-Flop/falling_edge_triggered_d_flipflop_tb.vcd
$date
	Thu Jan 05 20:46:21 2023
$end
$version
	Icarus Verilog
$end
$timescale
	1ns
$end
$scope module falling_edge_triggered_d_flipflop_tb $end
$var wire 1 ! q $end
$var reg 1 " clk $end
$var reg 1 # d $end
$var reg 1 $ reset $end
$var reg 1 % w $end
$scope module flipflop $end
$var wire 1 " clk $end
$var wire 1 # d $end
$var wire 1 $ reset $end
$var wire 1 % w $end
$var reg 1 ! q $end
$upscope $end
$upscope $end
$enddefinitions $end
$comment Show the parameter values. $end
$dumpall
$end
#0
$dumpvars
0%
1$
1#
0"
0!
$end
#1
0$
#2
1"
#3
0"
#4
1"
#5
0"
#6
1"
#7
0"
#8
1"
#9
0"
#10
1"
#11
0"
#12
1"
#13
0"
#14
1"
#15
0"
#16
1"
#17
0"
#18
1"
#19
0"
#20
1"
1%
#21
1!
0"
#22
1"
#23
0"
#24
1"
#25
0"
#26
1"
#27
0"
#28
1"
#29
0"
#30
1"
0#
#31
0!
0"
#32
1"
#33
0"
#34
1"
#35
0"
#36
1"
#37
0"
#38
1"
#39
0"
#40
1"
#41
0"
#42
1"
#43
0"
#44
1"
#45
0"
#46
1"
#47
0"
#48
1"
#49
0"
#50
1!
1"
1$
1#
#51
0!
0"
#52
1"
#53
0"
#54
1"
#55
0"
#56
1"
#57
0"
#58
1"
#59
0"
#60
1"
0$
0%
0#
#61
0"
#62
1"
#63
0"
#64
1"
#65
0"
#66
1"
#67
0"
#68
1"
#69
0"
#70
1"
#71
0"
#72
1"
#73
0"
#74
1"
#75
0"
#76
1"
#77
0"
#78
1"
#79
0"
#80
1"
1%
1#
#81
1!
0"
#82
1"
#83
0"
#84
1"
#85
0"
#86
1"
#87
0"
#88
1"
#89
0"
#90
1"
1$
#91
0!
0"
#92
1"
#93
0"
#94
1"
#95
0"
#96
1"
#97
0"
#98
1"
#99
0"
#100
1!
1"
0$
